zope/app/container/__init__.py
zope/app/container/btree.py
zope/app/container/configure.zcml
zope/app/container/constraints.py
zope/app/container/contained.py
zope/app/container/dependency.py
zope/app/container/directory.py
zope/app/container/find.py
zope/app/container/ftesting.zcml
zope/app/container/i18n.py
zope/app/container/interfaces.py
zope/app/container/ordered.py
zope/app/container/sample.py
zope/app/container/size.py
zope/app/container/testing.py
zope/app/container/traversal.py
zope/app/container/browser/__init__.py
zope/app/container/browser/add.pt
zope/app/container/browser/adding.py
zope/app/container/browser/commontasks.pt
zope/app/container/browser/configure.zcml
zope/app/container/browser/contents.pt
zope/app/container/browser/contents.py
zope/app/container/browser/find.pt
zope/app/container/browser/find.py
zope/app/container/browser/index.pt
zope/app/container/browser/meta.zcml
zope/app/container/browser/metaconfigure.py
zope/app/container/browser/tests/__init__.py
zope/app/container/browser/tests/configure.zcml
zope/app/container/browser/tests/index.txt
zope/app/container/browser/tests/test_adding.py
zope/app/container/browser/tests/test_contents.py
zope/app/container/browser/tests/test_contents_functional.py
zope/app/container/browser/tests/test_directive.py
zope/app/container/browser/tests/test_view_permissions.py
zope/app/container/tests/__init__.py
zope/app/container/tests/test_bwc_imports.py
zope_app_container-6.0.dist-info/licenses/LICENSE.txt
zope_app_container-6.0.dist-info/METADATA
zope_app_container-6.0.dist-info/WHEEL
zope_app_container-6.0.dist-info/top_level.txt
zope_app_container-6.0.dist-info/RECORD
