Metadata-Version: 2.4
Name: zope.app.container
Version: 6.0
Summary: Zope Container
Home-page: http://github.com/zopefoundation/zope.app.container
Author: Zope Foundation and Contributors
Author-email: zope-dev@zope.dev
License: ZPL-2.1
Keywords: zope3 container
Classifier: Development Status :: 5 - Production/Stable
Classifier: Environment :: Web Environment
Classifier: Intended Audience :: Developers
Classifier: License :: OSI Approved :: Zope Public License
Classifier: Programming Language :: Python
Classifier: Programming Language :: Python :: 3.9
Classifier: Programming Language :: Python :: 3.10
Classifier: Programming Language :: Python :: 3.11
Classifier: Programming Language :: Python :: 3.12
Classifier: Programming Language :: Python :: 3.13
Classifier: Programming Language :: Python :: Implementation :: CPython
Classifier: Programming Language :: Python :: Implementation :: PyPy
Classifier: Natural Language :: English
Classifier: Operating System :: OS Independent
Classifier: Topic :: Internet :: WWW/HTTP
Classifier: Framework :: Zope :: 3
Requires-Python: >=3.9
License-File: LICENSE.txt
Requires-Dist: setuptools
Requires-Dist: zope.browser
Requires-Dist: zope.browsermenu
Requires-Dist: zope.browserpage
Requires-Dist: zope.component
Requires-Dist: zope.container
Requires-Dist: zope.copypastemove
Requires-Dist: zope.dublincore>=3.7
Requires-Dist: zope.event
Requires-Dist: zope.exceptions
Requires-Dist: zope.i18n
Requires-Dist: zope.i18nmessageid
Requires-Dist: zope.interface
Requires-Dist: zope.lifecycleevent
Requires-Dist: zope.location
Requires-Dist: zope.publisher>=4.3.1
Requires-Dist: zope.security>=4.1.0
Requires-Dist: zope.size
Requires-Dist: zope.traversing
Provides-Extra: test
Requires-Dist: zope.app.appsetup; extra == "test"
Requires-Dist: zope.app.basicskin>=4.0; extra == "test"
Requires-Dist: zope.app.content; extra == "test"
Requires-Dist: zope.app.dependable>=4.0; extra == "test"
Requires-Dist: zope.app.http; extra == "test"
Requires-Dist: zope.app.pagetemplate>=4.0; extra == "test"
Requires-Dist: zope.app.principalannotation; extra == "test"
Requires-Dist: zope.app.publication; extra == "test"
Requires-Dist: zope.app.publisher; extra == "test"
Requires-Dist: zope.app.security; extra == "test"
Requires-Dist: zope.app.testing; extra == "test"
Requires-Dist: zope.app.wsgi; extra == "test"
Requires-Dist: zope.applicationcontrol; extra == "test"
Requires-Dist: zope.browser; extra == "test"
Requires-Dist: zope.browserresource; extra == "test"
Requires-Dist: zope.copypastemove; extra == "test"
Requires-Dist: zope.login; extra == "test"
Requires-Dist: zope.password; extra == "test"
Requires-Dist: zope.principalannotation; extra == "test"
Requires-Dist: zope.principalregistry; extra == "test"
Requires-Dist: zope.proxy>=4.2.1; extra == "test"
Requires-Dist: zope.securitypolicy; extra == "test"
Requires-Dist: zope.site; extra == "test"
Requires-Dist: zope.testbrowser>5; extra == "test"
Requires-Dist: zope.testing; extra == "test"
Requires-Dist: zope.testrunner>=6.4; extra == "test"
Dynamic: author
Dynamic: author-email
Dynamic: classifier
Dynamic: description
Dynamic: home-page
Dynamic: keywords
Dynamic: license
Dynamic: license-file
Dynamic: provides-extra
Dynamic: requires-dist
Dynamic: requires-python
Dynamic: summary
